crf_api_client/__init__.py
crf_api_client/base.py
crf_api_client/client.py
crf_api_client/exception.py
crf_api_client/models.py
crf_api_client/playground_agent.py
crf_api_client/table.py
crf_api_client/task.py
crf_api_client/tools.py
crf_api_client/warehouse.py
crf_api_client/operations/__init__.py
crf_api_client/operations/client_operations.py
crf_api_client/operations/warehouse_operations.py
crf_api_client-0.0.25.dist-info/licenses/LICENSE
crf_api_client-0.0.25.dist-info/METADATA
crf_api_client-0.0.25.dist-info/WHEEL
crf_api_client-0.0.25.dist-info/top_level.txt
crf_api_client-0.0.25.dist-info/RECORD
