Metadata-Version: 2.4
Name: crf-api-client
Version: 0.0.25
Summary: A client for the CRF API
Author: CRF
Requires-Python: >=3.11
License-File: LICENSE
Requires-Dist: requests==2.32.3
Requires-Dist: datamodel-code-generator==0.30.1
Requires-Dist: tqdm==4.67.1
Requires-Dist: pydantic>=2.10.6
Requires-Dist: openai>=1.99.9
Provides-Extra: dev
Requires-Dist: pytest==8.4.1; extra == "dev"
Requires-Dist: pytest-asyncio==1.1.0; extra == "dev"
Dynamic: license-file
